spln_sentiment_analysis/Token.py
spln_sentiment_analysis/Trie.py
spln_sentiment_analysis/__init__.py
spln_sentiment_analysis/parser.py
spln_sentiment_analysis/utils.py
spln_sentiment_analysis/datasetParsers/__init__.py
spln_sentiment_analysis/datasetParsers/leIA.py
spln_sentiment_analysis/datasetParsers/linguaKit.py
spln_sentiment_analysis/datasetParsers/parse.py
spln_sentiment_analysis/datasetParsers/sentilex.py
spln_sentiment_analysis/datasetParsers/utils.py
spln_sentiment_analysis/datasets/boosters.json
spln_sentiment_analysis/datasets/emojis.json
spln_sentiment_analysis/datasets/emojis.txt
spln_sentiment_analysis/datasets/lemmas.json
spln_sentiment_analysis/datasets/multiplier.txt
spln_sentiment_analysis/datasets/negate.json
spln_sentiment_analysis/datasets/words.json
spln_sentiment_analysis/datasets/LinguaKit/lex.txt
spln_sentiment_analysis/datasets/LinguaKit/train.txt
spln_sentiment_analysis/datasets/leIA/booster.txt
spln_sentiment_analysis/datasets/leIA/emojis.txt
spln_sentiment_analysis/datasets/leIA/negate.txt
spln_sentiment_analysis/datasets/leIA/vader_lexicon.txt
spln_sentiment_analysis/datasets/sentilex/sentilex.txt
spln_sentiment_analysis/tests/txt
spln_sentiment_analysis-1.0.3.dist-info/entry_points.txt
spln_sentiment_analysis-1.0.3.dist-info/WHEEL
spln_sentiment_analysis-1.0.3.dist-info/METADATA
spln_sentiment_analysis-1.0.3.dist-info/RECORD
