Metadata-Version: 2.1
Name: spln_sentiment_analysis
Version: 1.0.3
Summary: Name 
Author-email: lumafepe <lumafepe@gmail.com>, tiago-bacelar <pereira.migueltiago@gmail.com>
Requires-Python: >=3.8
Classifier: License :: OSI Approved :: MIT License
Requires-Dist: jjcli>=0.1.23
Requires-Dist: unidecode>=1.3.8
